[
  {
    "i": "http://img3.fengniao.com/forum/attachpics/5/98/179414.jpg", 
    "d": "<div dir=\"ltr\">北京北堂（救世主堂）  (教堂)\t<br><br>010-66175198<br>北京市西城区西什库大街33号<br><br>救世主堂始建于1888年，又称北堂。最初在中南海紫光阁以西，羊房夹道(即养蜂夹道)以南名叫蚕池口的地方，因此也叫蚕池口教堂。康熙四十二年(1703)建成。光绪十二年(1886)蚕池口天主教堂迁移到西什库内重建。北堂属哥特式建筑，大堂平面呈十字架形状，建筑面积约2200平方米，高16．5米，钟楼塔尖高约31米。堂前有月台，三面有汉白玉石栏杆，大堂内有主祭台、苦难堂和唱经楼。大堂正门两旁，有中国式建筑碑亭两座。北堂所属建筑包括修道院、图书馆、后花园、印刷厂、孤儿院等。 <br>", 
    "g": "116.379158,39.924316,0.000000", 
    "n": "北京北堂（救世主堂）  "
  }, 
  {
    "i": "http://zdche.com/forum/attachments/0PvO5MPFMg==_hStvtqYYWzc9.jpg", 
    "d": "<div dir=\"ltr\">北京南堂（圣母无原罪）  (教堂)\t<br><br>010-66087238<br>北京市西城区前门西大街141号（宣武门地铁站）<br><br>南堂大堂是哥特式拱券形建筑，建筑面积约1300平方米，附属建筑约400平方米。南堂内有原教堂石碑二，其一为清世祖御制天主堂碑记，今已字迹不清，嵌于大堂前两侧墙壁上，大堂西墙原竖立的铁十字架，约高1丈2尺，系南堂最早的遗物也为北京市重点保护文物。它有三进院子，中式主入口内的第一进院里以圣母山为主，东院为教堂，西跨院是住房。此外还有天文台、藏书楼等。东院的教堂正立面朝南，为巴洛克式，室内则采用了罗马式的手法，其中三个雄伟而不失细腻的拱门将入口妆点得很有特点。<br>", 
    "g": "116.375214,39.900486,0.000000", 
    "n": "北京南堂（圣母无原罪）  "
  }, 
  {
    "i": "http://zdche.com/forum/attachments/zfW4rr6uMQ==_NSWe1fYGXS90.jpg", 
    "d": "<div dir=\"ltr\">北京东堂（若瑟堂）  (教堂)\t<br><br>010-65240643<br>北京市东城区王府井大街74号<br><br>东堂位于北京著名的王府井大街。最早建于1655年，原来是清朝顺治皇帝赐给两位外国神父的住宅。他们两个人就在在空地上建了一座小教堂，后由于地震和战乱曾多次被毁。1904年重新修建建，后至1980年经修复后重新开堂。由于地理位置的关系，东堂的正立面朝西。它的建筑形式是罗马式，里面有粗壮的壁柱，一高两低的穹隆形圆顶，奠定了它浑厚的风格。2000年，为了配合王府井大街扩建工程，北京市政府拨款1.3亿元将教堂内外整修一新，拆除院墙，扩建堂前广场，还加了喷泉地灯等设备。<br>", 
    "g": "116.412224,39.917175,0.000000", 
    "n": "北京东堂（若瑟堂）  "
  }, 
  {
    "i": "http://zdche.com/forum/attachments/zvfMww==_aloP1aaZEpV1.jpg", 
    "d": "<div dir=\"ltr\">北京西堂  (教堂)<br><br>010-66156619<br>北京市西城区西直门内大街130号<br><br>西堂在西直门内大街南侧，是这四座堂中的历史最年轻的教堂，最早建于1723年，1912年重修。因为它旁边的药厂未能迁出，所以在大街上几乎看不到它的模样。不过教堂内部有精美的科林斯柱子及哥特式的尖拱券，使堂内高大雄伟、秀丽而庄严。<br>", 
    "g": "116.365791,39.940277,0.000000", 
    "n": "北京西堂  "
  }, 
  {
    "i": "http://zdche.com/forum/attachments/tqu9vMPxz+8x_Bnr7w2eiJrTn.jpg", 
    "d": "<div dir=\"ltr\">圣弥额尔天主堂（圣弥厄尔）  (教堂)<br><br>010-65135170<br>北京市东城区东交民巷甲13号<br><br>东交民巷天主教堂始建于1901年，清朝末年东交民巷是外国人的特区，几乎所有的大使馆都建在这里。东交民巷天主教堂原是为住在这里的外国人专门建的，现在划归北京教区所有。入口在南，从外到内都是典型的哥特式建筑，三个主尖塔和多个尖塔状装饰物上下呼应，相得益彰有质。 <br>", 
    "g": "116.409286,39.902954,0.000000", 
    "n": "圣弥额尔天主堂（圣弥厄尔）  "
  }, 
  {
    "i": "http://zdche.com/forum/attachments/xM+42tfTtcLA3w==_2eV6ZtxglIyw.jpg", 
    "d": "<div dir=\"ltr\">圣德肋撒堂（南岗子）  (教堂)\t<br><br>010-67143341<br>北京市崇文区幸福大街永生巷6号<br><br>南岗子天主堂，原称作普爱堂，建于1910年，由两栋双层楼及一些平房组成，占地面积43.5亩，是北京仁爱会修女和若瑟会修女集资两万银元在原放生池（今永生巷）购买的一块地而建成的。该堂主要用于修女们疗养、静修之用，并开设诊所，后增设缝纫班，义务为穷人和大龄孤儿及社会上贫困的女孩子提供服务。<br>", 
    "g": "116.427353,39.888763,0.000000", 
    "n": "圣德肋撒堂（南岗子）  "
  }, 
  {
    "i": "http://www.bjjdt.com/xiashu/xiashudanwei.files/4.jpg", 
    "d": "<div dir=\"ltr\">北京崇文门教堂  (教堂)\t<br><br>010-65242193<br>北京市崇文门内后沟胡同丁2号<br><br>崇文门教堂是北京市目前最古老的一座基督教新教教堂，也是一所涉外的教堂，在国内外享有一定声誉，曾经接待过美国前总统乔治·布什、克林顿 , 英国坎特伯雷大主教乔治·凯瑞博士，著名的布道家葛培理牧师也曾经多次来访。每个主日都有外国使馆的官员、国外信徒来此做礼拜，经常有国际教会间的交流活动。 <br>", 
    "g": "116.420250,39.902462,0.000000", 
    "n": "北京崇文门教堂  "
  }, 
  {
    "i": "http://www.bjjdt.com/xiashu/xiashudanwei.files/haidian.gif", 
    "d": "<div dir=\"ltr\">海淀堂  (教堂)<br><br>010-62572902、010-82613772<br>北京市海淀区彩和坊路9号<br><br>海淀基督教会，前称海淀中华基督教会，原是北京公理会所属的一个福音布道所。由于信徒逐日增多，在众信徒和董事们的共同努力下，1933年募款4600余银圆，于1933年6月建成现在的大礼拜堂，当时信徒增至五百人左右。<br>", 
    "g": "116.308632,39.977467,0.000000", 
    "n": "海淀堂  "
  }, 
  {
    "i": "http://www.bjjdt.com/xiashu/xiashudanwei.files/6.gif", 
    "d": "<div dir=\"ltr\">珠市口教堂  (教堂)\t<br><br>010-63016678<br>北京市崇文区前门大街129号<br><br>珠市口教堂始建于1921年，原属卫理公会，1923年建成后，成为基督教美以美会北京教区四大堂之一，几十年来始终为宗教活动场所，1966年因文革被迫停止活动，1980年落实政策，经过维修，1988年起恢复了活动，座西朝东，正面临前门大街，主楼一座三层，临街为灰砖砌筑，内部为钢筋水泥结构。<br>", 
    "g": "116.397827,39.898247,0.000000", 
    "n": "珠市口教堂  "
  }, 
  {
    "i": "http://www.bjjdt.com/xiashu/xiashudanwei.files/5.gif", 
    "d": "<div dir=\"ltr\">缸瓦市堂  (教堂)<br><br>010-66176181<br>北京市西城区西四南大街57号<br><br>缸瓦市教堂于1903年建堂，原属于英国伦敦会。1922年改建新堂，并加入“中华基督教会”，现在，缸瓦市堂有信徒5000多人，每个主日都有四次礼拜。<br>", 
    "g": "116.373215,39.921471,0.000000", 
    "n": "缸瓦市堂  "
  }, 
  {
    "i": "http://www.bjjdt.com/xiashu/xiashudanwei.files/kuanjie.jpg", 
    "d": "<div dir=\"ltr\">宽街教堂  (教堂)<br><br>010-84039432<br>北京市东城区地安门东大街吉祥胡同10号<br><br>宽街教堂位于店门东大街，是一所历史悠久的基督教堂。<br>", 
    "g": "116.400574,39.933270,0.000000", 
    "n": "宽街教堂  "
  }, 
  {
    "i": "http://www.bjjdt.com/xiashu/xiashudanwei.files/chaoyong.gif", 
    "d": "<div dir=\"ltr\">朝阳教堂  (教堂)<br><br>010-64330699、010-64330655<br>北京市朝阳区东四环北路东风桥东风南路60号<br><br>朝阳教堂建于2003年，是中国政府为满足广大教会成员需要而建立的，于2005年9月12日教堂建成交于北京基督教两会使用，基督教两会对新堂进行了装修。2005年12月11日举行感恩礼拜，12月16日献堂，开始正式使用。<br>", 
    "g": "116.490463,39.952961,0.000000", 
    "n": "朝阳教堂  "
  }, 
  {
    "i": "http://www.bjjdt.com/xiashu/xiashudanwei.files/88.jpg", 
    "d": "<div dir=\"ltr\">丰台教堂  (教堂)<br><br>010-87500214、010-87500470<br>北京市丰台区草桥世界花卉大观园西门南侧<br><br>丰台堂兴建于04年，教堂外形独特，像开屏的孔雀，体现了万物的美好，又如一只圆号，传出耶稣基督的美妙福音。俯视丰台堂则呈螺旋形状，具有强烈的动感，体现了世间万物和人类的活力，也显示出基督教千年来所具有的强大生命力。钟塔由两道弧墙组成人字与十字架形成完美的组合，向人们述说着这是一条永生之路。<br>", 
    "g": "116.305893,39.830933,0.000000", 
    "n": "丰台教堂  "
  }
]